suitcase/mongo_embedded/__init__.py
suitcase/mongo_embedded/_version.py
suitcase/mongo_embedded/conftest.py
suitcase/mongo_embedded/tests/__init__.py
suitcase/mongo_embedded/tests/conftest.py
suitcase/mongo_embedded/tests/fixtures.py
suitcase/mongo_embedded/tests/tests.py
suitcase/mongo_normalized/__init__.py
suitcase/mongo_normalized/_version.py
suitcase/mongo_normalized/tests/__init__.py
suitcase/mongo_normalized/tests/conftest.py
suitcase/mongo_normalized/tests/fixtures.py
suitcase/mongo_normalized/tests/tests.py
suitcase_mongo-0.7.0.dist-info/LICENSE
suitcase_mongo-0.7.0.dist-info/METADATA
suitcase_mongo-0.7.0.dist-info/WHEEL
suitcase_mongo-0.7.0.dist-info/top_level.txt
suitcase_mongo-0.7.0.dist-info/RECORD
