Metadata-Version: 2.2
Name: suitcase-mongo
Version: 0.7.0
License: BSD (3-clause)
Classifier: Development Status :: 2 - Pre-Alpha
Classifier: Natural Language :: English
Classifier: Programming Language :: Python :: 3.6
License-File: LICENSE
Requires-Dist: event-model>=1.8.0rc2
Requires-Dist: pymongo
Dynamic: classifier
Dynamic: description
Dynamic: description-content-type
Dynamic: license
Dynamic: requires-dist
